{
  "title":"Waranga News | Advertisements",
  "sling:resourceType":"wnews/page/list",
  "jcr:primaryType":"nt:unstructured",
  "list": {
    "sling:resourceType":"wnews/block/advertisement-list",
    "cottage-ice-cream-shoppe": {
      "sling:resourceType": "wnews/page/advertisement",
      "title": "The Cottage Ice Cream Shoppe",
      "media": "s3./wnews/Cottage-Ice-Cream-Shoppe.png",
      "testimonials": "enabled",
      "disqusShortName": "waranganews",
      "published": true
    },
    "criterion-hotel-accommodation": {
      "sling:resourceType": "wnews/page/advertisement",
      "title": "The Criterion Hotel",
      "media": "s3./wnews/Criterion-Hotel-accomm.png",
      "testimonials": "enabled",
      "disqusShortName": "waranganews",
      "published": true
    },
    "old-imperial-hotel": {
      "sling:resourceType": "wnews/page/advertisement",
      "title": "The Old Imperial Hotel",
      "media": "s3./wnews/Imperial-Hotel.png",
      "testimonials": "enabled",
      "disqusShortName": "waranganews",
      "published": true
    },
    "king-billy-retreat": {
      "sling:resourceType": "wnews/page/advertisement",
      "title": "King Billy Retreat",
      "media": "s3./wnews/King-Billy-Retreat.png",
      "testimonials": "enabled",
      "disqusShortName": "waranganews",
      "published": true
    },
    "campbell-smith": {
      "sling:resourceType": "wnews/page/advertisement",
      "title": "Campbell Smith",
      "media": "s3./wnews/Campbell-Smith.png",
      "testimonials": "enabled",
      "disqusShortName": "waranganews",
      "published": true
    },
    "clinical-massage": {
      "sling:resourceType": "wnews/page/advertisement",
      "title": "Clinical Massage",
      "media": "s3./wnews/Clinical-Massage.png",
      "testimonials": "enabled",
      "disqusShortName": "waranganews",
      "published": true
    },
    "clive-coventry": {
      "sling:resourceType": "wnews/page/advertisement",
      "title": "Clive Coventry",
      "media": "s3./wnews/Clive-Coventry.png",
      "testimonials": "enabled",
      "disqusShortName": "waranganews",
      "published": true
    },
    "coghlans-iga": {
      "sling:resourceType": "wnews/page/advertisement",
      "title": "Coghlans IGA",
      "media": "s3./wnews/Coghlans-IGA.png",
      "testimonials": "enabled",
      "disqusShortName": "waranganews",
      "published": true
    },
    "mud-hut-joga": {
      "sling:resourceType": "wnews/page/advertisement",
      "title": "Mud Hut Yoga",
      "media": "s3./wnews/Mud-Hut-Yoga-proof.png",
      "testimonials": "enabled",
      "disqusShortName": "waranganews",
      "published": true
    },
    "lorem-ipsum-2": {
      "sling:resourceType": "wnews/page/advertisement",
      "title": "Lorem ipsum dolor sit amet.",
      "media": "placeholder.png/200x200"
    }
  }
}
